Workbook

Sheet Investors
A1: Go live dates | B1: LF | C1: Shorts | D1: Status | E1: Assets | F1: Column 1 | I1: Learnings:
A2: 45962 | B2: Gold rush | D2: Published | E2: S1: Gold Rush - Storyboarding | I2: Published 5 factors IPO - on Monday (10pm) -- didn't pick that well; Traffic source proportion from Yt features not much; lesser impressions
A3: 45965 | C3: Gold rush shorts 1 | D3: Published
A4: 45968 | C4: Gold rush shorts 2 | D4: Published
A5: 45967 | B5: Emerging Themes | D5: Published | E5: S02 - Emerging Themes
A6: 45970 | C6: ET Shorts 1 | D6: Published
A7: 45971 | C7: ET Shorts 2 | D7: Published
A8: 45975 | B8: PE Ratio | D8: Published | E8: S03 - How to make sense of PE Ratio?
A9: 45977 | C9: PE Shorts 1 | D9: Published
A10: 45978 | C10: PE Shorts 2 | D10: Published
A11: 45979 | C11: PE Shorts 3 | D11: Published
A12: 45981 | B12: ROCE | D12: Published | E12: S04 - How to make sense of ROCE?
A13: 45982 | C13: ROCE Shorts 1 | D13: Published
A14: 45983 | C14: ROCE Shorts 2 | D14: Published
A15: 45985 | B15: 5 Factors - IPO | D15: Published | E15: S05 - Top 5 Factors to check before IPO
A16: 45987 | C16: IPO Shorts 1 | D16: Published
A17: 45989 | C17: IPO Shorts 2 | D17: Ready
A18: 45989 | B18: Is Stock Market Overvalued | D18: Published | E18: S06 - Is the Indian Stock Market Overvalued?
A19: 45990 | C19: SM Shorts 1 | D19: Published
A20: 45992 | C20: SM Shorts 2 | D20: Published
A21: 45993 | C21: SM (BTS)
A22: 45994 | B22: Emerging Themes Part 2 | D22: Published | E22: S07 - Emerging Themes Part 2
A23: 45997 | C23: ET Part 2 - Teaser/BTS | D23: Published | I23: What i learned about investing from Darwin -- (after we build some traction)
A24: 45998 | C24: ET Shorts 1 | D24: Published | H24: Teaser: Community post; IG Story; Linkedin post; TL; WA | I24: Long form topics
A25: 45999 | C25: ET Shorts 2 | D25: Published | I25: Where are DIIs putting in their money? - India investing in itself DII - FII | J25: 2026 Special??
A26: 46000 | B26: Art of picking of stocks | D26: Published | E26: S08 - Art of picking stocks | I26: Battle of the asset classes -
A27: 46004 | C27: Art of picking stocks 1 | D27: Ready | I27: Lucky vs avg vs unlucky investor
A28: 46005 | C28: Art of picking stocks 2 | D28: Ready | I28: Shorts
A29: 46003 | B29: ICICI Prudential AMC IPO | D29: Published | E29: ICICI Prudential Asset Management Company IPO
A30: 46003 | C30: ICICI IPO Shorts | D30: Published
A31: 46005 | B31: Debt to Equity | D31: Published | E31: S09 - Debt to Equity | I31: Passive income is a scam!
A32: 46006 | C32: DE Shorts 1 | D32: Published | I32: SIF
A33: 46007 | C33: DE Shorts 2 | D33: Published
A34: 46008 | B34: ROE | D34: Published | E34: S10 - ROE
A35: 46010 | C35: ROE Shorts 1 | D35: Published
A36: 46011 | C36: ROE Shorts 2 | D36: Published
A37: 46011 | B37: Best performing Stocks of 2025 | D37: Published | E37: S11: Top stocks of 2025 | H37: 10th Thursday
A38: 46012 | B38: FILLER SHORTS | C38: 3 Sectors for 2026 | D38: Published
A39: 46014 | C39: Best performing stocks shorts 1 | D39: Published
A40: 46016 | C40: Best performing stocks shorts 2 | D40: Published
A41: 46018 | B41: Top 3 ETFs to invest in? | D41: Published | E41: S13 - Battle of Asset classes | H41: 16th Tuesday
A42: 46019 | B42: FILLER SHORTS | C42: Stock market wrap | D42: Published | E42: Shorts S02 - Year wrap | H42: 24th, Wednesday | I42: 24th -- Auto stocks & What FIIs & DIIs
A43: 46020 | B43: FILLER SHORTS | C43: US themes | D43: Published | E43: S03 - US emerging themes
A44: 46023 | C44: Top 3 ETFs to invest shorts 1 | D44: Published | H44: 24th, Wednesday
A45: 46024 | C45: Top 3 ETFs to invest shorts 2 | D45: Published | H45: ??
A46: 46025 | B46: Battle of asset classes | D46: Published | E46: S12: Top 3 ETFs for your portfolio in 2026 | I46: 30th -- Stock market wrap
A47: 46028 | C47: Battle of asset classes shorts 1 | D47: Published
A48: 46029 | C48: Battle of asset classes shorts 2 | D48: Published
C49: Evergreen stocks discarded - & reshot | H49: 22nd, Monday
A50: 46032 | B50: Tobacco stocks | D50: Published | E50: S16 - Tobacco | H50: 30th??
A51: 46035 | C51: Tobacco stocks shorts 1 | D51: Published
A52: 46036 | B52: FILLER SHORTS | C52: Battle of asset classes - EXP/ tobacco stocks shorts 2
A53: 46040 | B53: What FIIs & DIIs are buying | D53: Published | E53: S15 - What are FIIs & DIIs buying? | H53: 2nd Jan | I53: Delayed because of technical delay's from Money media's end
A54: 46042 | C54: FIIs & DIIs shorts 1 | D54: Published
A55: 46043 | B55: Gold vs Silver Surge | D55: Published | E55: S17 - Gold vs Silver | H55: Nock + Internal
A56: 46044 | C56: Gold vs Silver Shorts 1 | D56: Published
A57: 46045 | B57: Sectors to watch Before Budget | D57: Published | H57: Shoot - Friday - 16th - MM
A59: 46047 | B59: Top 5 High Growth Undervalued stocks - Indian feel | D59: Published | H59: Shoot - Friday - 16th - Nock
A60: 46048 | C60: Sectors to watch Shorts 1 | D60: Published
A61: 46049 | C61: Sectors to watch Shorts 2 | D61: Published
A62: 46050 | B62: Evergreen stocks | D62: Published | E62: S14 - Evergreen stocks | H62: Nock
A63: 46051 | C63: Evergreen stocks shorts 1 | D63: Published
C64: Gold silver shorts 3 | D64: Shot
A65: 46052 | B65: EU Shorts - Native | D65: Published
C66: Gold silver shorts 2 | D66: Ready
A67: 46055 | C67: Evergreen stocks shorts 2 | D67: Published | I67: EU deal - shorts
A68: 46053 | B68: Metals | D68: Ready | H68: 20th, Tuesday shoot. - Nock
A69: 46054 | C69: Metals Shorts 1 | D69: Shot
C70: Metals Shorts 2 | D70: Shot
A71: 46056 | B71: Sectors to watch after Budget | D71: Published | H71: 2nd Feb shoot - Money Media
A72: 46057 | C72: High growth shorts | D72: Published
A73: 46058 | C73: Large cap Shorts 1 | D73: Published
A74: 46059
A75: 46060 | B75: Mutual Fund vs ETFs | D75: Published | H75: Shoot - 30 Jan - Nock
A76: 46062 | C76: Mutual funds vs ETF Shorts 2 | D76: Published
A77: 46063 | C77: Mutual funds vs ETF Shorts 1 | D77: Shot
A78: 46065 | B78: Large cap stocks | D78: Published | H78: Shoot - 2/3feb
A79: 46068 | C79: Large cap shorts 2 - Eicher | D79: Published
A80: 46069 | C80: Silver - dollar | D80: Shot | H80: SB - 11th feb
A81: 46070 | B81: REITs Vs inVitS | D81: Published
A82: 46072 | B82: 5 Hidden Gems | D82: Published | H82: shoot - 10 feb | I82: 50k
A83: 46073 | D83: Ready
A84: 46074 | C84: Shorts 1 - screener query | D84: Published | O84: =20*8 -> 160
A85: 46075 | B85: Metals | D85: Published | I85: 15k | M85: Jan | N85: 144
A86: 46076 | C86: Metals Shorts 1 | D86: Published | M86: Feb | N86: 150 | P86: =N86/8 -> 18.75
A87: 46077 | C87: Metals Shorts 2 | D87: Published | M87: March | N87: 330 | P87: 35k-40k
A88: 46078 | C88: Solar panels - Trending | D88: Published | E88: S25 - 10 Stocks after Earnings result | H88: shoot - 18 feb | I88: 15k | N88: 625 | R88: =8*30 -> 240
A89: 46079 | B89: Strong Q3 Results w strong fundamentals | D89: Published | R89: =330-R88 -> 90 | S89: =R89/16 -> 5.625
A90: 46080 | C90: REITs Shorts 1 | D90: Ready
A91: 46081 | B91: Mid cap companies - comment small cap | D91: Published | E91: S26 - Mid cap companies | H91: shoot - 20 feb | I91: 10k | L91: 57178
A92: 46083 | C92: Hero shorts - mid cap | D92: Published | L92: =L91+80000 -> 137178 | R92: =32*8 -> 256 | S92: =330-R92 -> 74
C93: Solar industries - earnings | D93: Shot | I93: =50+15+5+10 -> 80 | O93: =330/8 -> 41.25 | S93: =S92/16 -> 4.625
A94: 46085 | B94: Cardinal sins of investing | D94: Published
A95: 46086 | C95: Force motors- hidden gem | D95: Published
A96: 46087 | C96: AU finance bank - mid cap | D96: Published
A97: 46088 | B97: Top 3 mutual funds and their 3 biggest bets | D97: Published | H97: shoot - 23 feb
A98: 46090 | C98: Praga Parikh | D98: Shot
A99: 46091 | C99: War shorts 1 | D99: Published
A100: 46092 | B100: Small cap Companies | D100: Published | H100: shoot - 24 feb
A101: 46093 | C101: War shorts 2 | D101: Published
...

Sheet Finone
A1: Go live dates | B1: LF | C1: Shorts | D1: Status | E1: Assets | F1: Column 1
A2: 46100 | C2: Maharashtra Debt Crisis | D2: Published
A3: 20 | B3: 5 rules of Warren Buffett | C3: Re: Money vs Wealth | D3: Published
A4: 21 | C4: Brent Crude | D4: Ready
A5: 23 | C5: Jamnagar Oil | D5: Ready
A6: 24 | C6: Re: Warren Buffett | D6: Edit WIP
A7: 25 | B7: Has AI Finally Cracked IT | D7: Ready
A8: 26 | C8: Gold is falling amidst | D8: Scripting
A9: 27
A10: 29
A11: 46111
A12: 31
A13: 46113
A14: 2 | B14: LF
A15: 3
A16: 46116
C128: Top 3 stocks
I131: 28
I132: 9
I133: =sum(I131:I132) -> 37

Sheet Markets
A1: Date | B1: Topic | C1: Content Type | D1: Status | E1: Agency
A2: 46090 | B2: Tax Loss Harvesting | C2: Shorts | D2: Live | E2: Shubh
A3: 46091 | B3: 1st half - Poll (20%+ CAGR) | C3: Poll | D3: Live
A4: 46091 | B4: 2nd Half - EPF vs PPF vs NPS vs MF | C4: Shorts | D4: Editing | E4: Shubh
A5: 46092 | B5: 7 equity MF over 20% CAGR | C5: Long Form | D5: Editing | E5: Mango
A6: 46093 | B6: 7 equity MF over 20% CAGR | C6: Shorts
A7: 46094 | B7: 1st Half - Poll (around tax harvesting) | C7: Poll
A8: 46094 | B8: Some old topic | C8: Shorts
A9: 46095 | B9: Tax Harvesting | C9: Long Form | D9: Editing | E9: Shubh
A10: 46096 | B10: Tax Harvesting another shorts | C10: Shorts
A11: 46097 | B11: 1st Half - Poll | C11: Poll
A12: 46097 | B12: 2nd half - shorts | C12: Shorts
A13: 46098 | B13: shorts | C13: Shorts
A14: 46099 | B14: Generate monthly income from your investments | C14: Long Form | D14: Editing | E14: Shubh
A15: 46100 | B15: shorts | C15: Shorts
A16: 46101 | B16: 1st Half - Poll | C16: Poll
A17: 46101 | B17: 2nd half - Shorts | C17: Shorts
A18: 46102 | B18: Global Investing | C18: Long Form | D18: Shot | E18: Mango
A19: 46103 | B19: shorts | C19: Shorts
A20: 46104 | B20: shorts | C20: Shorts
A21: 46105 | B21: 1st half - Poll | C21: Poll
A22: 46105 | B22: 2nd half - Shorts | C22: Shorts
A23: 46106 | B23: Life Cycle fund | C23: Long Form | D23: Editing | E23: Mango
A24: 46107 | B24: Shorts | C24: Shorts
A25: 46108 | B25: 1st Half - poll | C25: Poll
A26: 46108 | B26: 2nd half - shorts | C26: Shorts
A27: 46109 | B27: Multicap vs flexi vs large & Mid Cap | C27: Long Form | D27: Scripting
A28: 46110 | B28: shorts | C28: Shorts
A29: 46111 | B29: shorts | C29: Shorts
A30: 46112 | B30: Poll | C30: Poll
A31: 46113 | B31: Are MF too similar now? | C31: Long Form | D31: Research
A32: 46114 | B32: shorts | C32: Shorts
A33: 46115 | B33: 1st half - poll | C33: Poll
A34: 46115 | B34: 2nd half - shorts | C34: Shorts
A35: 46116 | B35: Are we entering low decades for equities | C35: Long Form | D35: Research
A36: 46117
A37: 46118
A38: 46119
A39: 46120 | B39: FII vs DII | C39: Long Form | D39: Research
A40: 46121
A41: 46122
A42: 46123 | B42: All Weather Ray Dalio's Portfolio | C42: Long Form | D42: Research
A43: 46124
A44: 46125
A45: 46126
A46: 46127 | C46: Long Form
A47: 46128
A48: 46129
A49: 46130 | C49: Long Form
A50: 46131
A51: 46132
A52: 46133
A53: 46134 | C53: Long Form
A54: 46135
A55: 46136
A56: 46137 | C56: Long Form
A57: 46138
A58: 46139
A59: 46140
A60: 46141 | C60: Long Form
A61: 46142

Sheet Main
A1: Go live dates | B1: LF | C1: Shorts | D1: Status | E1: Assets | F1: POC | G1: Shoot
A2: 46029 | C2: Bharat Coking Coal IPO | D2: Published | F2: Swati
A3: 46030 | B3: HDFC | D3: Published | F3: Swati
A4: 46032 | B4: Why MRF's stock is the most expensive? | D4: Published | F4: Swati
A5: 46034 | C5: Amagi Media IPO | D5: Published | F5: Swati
A6: 46035 | C6: HDFC Shorts 2 | D6: Published | F6: Swati
A7: 46036 | C7: MRF Shorts 1 | D7: Published | F7: Swati
A8: 46036 | B8: Capital Stocks | D8: Published | F8: Swati
A9: 46039 | C9: Capital shorts 1 | D9: Published | F9: Swati
A10: 46041 | C10: Shadowfax IPO | D10: Published | F10: Sanika
A11: 46042 | C11: Capital Shorts 2 | D11: Published | F11: Swati
A12: 46043 | B12: Power Stocks | D12: Published | F12: Aparna
A13: 46044 | C13: Power Stocks Shorts 1 | D13: Published | F13: Aparna
A14: 46045 | C14: Power Stocks Shorts 2 | D14: Published | F14: Aparna
A15: 46046
A16: 46047
A17: 46048 | B17: High growth, undervalued stocks (Republic day special) | D17: Published | F17: Aparna
A18: 46049 | C18: Shorts 1 | D18: Shot | F18: Aparna
A19: 46050
A20: 46054 | C20: Budget Shorts | D20: Published | F20: Aparna
A21: 46055 | B21: Budget Day | D21: Published | F21: Aparna | G21: Shoot - 2nd Feb
A22: 46056 | C22: NFO Shorts | D22: Published | F22: Swati
A23: 46057 | C23: India US Trade Deal | D23: Published | F23: Aparna
A24: 46060 | B24: Auto Stocks | D24: Published | F24: Aparna
A25: 46062 | B25: Aye IPO | D25: Published | F25: Aparna
A26: 46062 | B26: Fractal Analytics IPO | D26: Published | F26: Swati
A27: 46063 | C27: Auto stocks shorts 1 | D27: Published | F27: Aparna
A28: 46064 | C28: Auto stocks shorts 2 | D28: Ready | F28: Aparna
A29: 46064 | B29: Metals | D29: Published | F29: Aparna | G29: Wed
A30: 46065 | D30: Shot | F30: Swati
A31: 46066 | C31: Silver as currency hedge | D31: Shot | F31: Aparna | G31: SB - 11th Feb
A32: 46070 | B32: Hospital Stocks | D32: Published | F32: Swati
C33: Hospital Stocks Shorts 1 | D33: Published
A34: 46071 | C34: Hospital Stocks Shorts 2 | D34: Ready
A35: 46072
A36: 46074 | B36: Banking Stocks | D36: Published | F36: Swati | G36: Storyboarding
C37: Banking Stocks Shorts 1 | D37: Published
C38: Banking Stocks Shorts 2 | D38: Published
A39: 46075 | C39: IPO Shorts - Clean max | D39: Published | F39: Swati | L39: 2500000
A40: 46076 | C40: IPO Shorts - Reva | D40: Published | F40: Aparna | K40: Jan | L40: 476760
A41: 46077 | C41: IPO - Omnitech | D41: Published | F41: Aparna
A42: 46077 | C42: AI - trend | D42: Published | F42: Raghav
A43: 46078 | C43: Trending - Solar Crash | D43: Published | F43: Aparna
A44: 46078 | B44: Cement Stocks | D44: Published | F44: Aparna | G44: Shoot - 9feb | H44: SB - 11th Feb | K44: Feb | L44: 402200
A45: 46080 | C45: AYNTK | D45: Published | F45: Raghav
A46: 46080 | C46: Alcohol stocks shorts 1 | D46: Published | F46: Swati
A47: 46081 | C47: NFO | D47: Published | F47: Swati
A48: 46081 | B48: Alcohol Stocks | D48: Published | F48: Swati | G48: Shoot - 9th Feb | H48: SB - 11th Feb
A49: 46082 | C49: Banking shorts 2 | D49: Published | F49: Aparna
A50: 46086 | C50: Alcohol stocks shorts 1 | D50: Published | F50: Swati
A51: 46085 | C51: AYNTK | F51: Raghav
A52: 46085 | C52: IPO | D52: Published | F52: Swati
A53: 46086 | B53: Textile Stocks | D53: Published | F53: Aparna | L53: Avg. views | M53: 30000 | N53: 15000 | O53: 20000
A54: 46087 | C54: LPG Shorts | F54: Raghav
A55: 46087 | C55: Alcohol stocks shorts 2 | D55: Published | F55: Swati
A56: 46088 | B56: Product video | E56: 0.41666667
A57: 46088 | C57: AYNTK/Hospital | D57: Published | E57: evening | F57: Raghav
A58: 46089 | B58: IT Stocks | D58: Published | E58: morning | F58: Swati
A59: 46089 | C59: Cement shorts 1/textile | D59: Published | E59: evening | F59: Aparna
A60: 46090 | C60: Textile shorts 1 | D60: Published
A61: 46091 | C61: InviTs | D61: Published
A62: 46092 | B62: War Impact | D62: Published | F62: Swati
A63: 46093 | B63: ABC Teaser | C63: IT Shorts 1 | D63: Published
A64: 46094 | C64: Textile shorts 2
A65: 46095 | B65: Solar Stocks | D65: Published | F65: Swati | G65: Shoot - 24th Feb | L65: Total | M65: =#REF!*M53 -> #REF! | N65: =#REF!*N53 -> #REF! | O65: =#REF!*O53 -> #REF!
A66: 46096 | C66: Solar Shorts 1 | F66: Swati
A67: 46097 | C67: Solar Shorts 2 | F67: Swati | L67: Sum of all Categ | M67: =SUM(M65:O65) -> #REF!
A68: 46099 | B68: FMCG Stocks | D68: Published | F68: Swati | K68: =#REF!*70% -> #REF!
A69: 46100 | C69: IPO | D69: Published | F69: Aparna
A70: 46101 | C70: HDFC - Trending | D70: Published | F70: Raghav | M70: =K68-M67 -> #REF!
A71: 46103 | B71: War Impact - Part 2 | D71: Published | F71: Aparna
A72: 46102 | C72: Market crash | D72: Published | F72: Raghav
A73: 46102 | B73: AYNTK - LF | D73: Published | F73: Raghav
A74: 46104 | C74: IPO - Powerica | D74: Published | F74: Aparna
A75: 46104 | C75: Product- Margin trading | D75: Published
A76: 46104 | C76: Trending- gold prices | D76: Published | F76: Raghav
A77: 46105 | C77: Trending- why is Indian SM reacting to the war? | D77: Shot | F77: Aparna
A78: 46106 | B78: How Titan became a giant? | D78: Shot | F78: Aparna
A79: 46107 | C79: Ozempic | F79: Aparna
A80: 46108 | B80: MTF - Prod video | D80: Shot | F80: Raghav
A81: 46108 | B81: Brand film
A82: 46109 | C82: AYNTK- Royal enfield | H82: 2 Non social slots
A83: 46110 | C83: Any pending shorts? | F83: Swati
A84: 46111 | B84: Wire & Cable Stocks | D84: Shot | F84: Aparna | H84: 25th March- shoot
A85: 46112
A86: 46113
A87: 46114 | B87: GLP -1 | D87: Shot | F87: Aparna | H87: 25th March- shoot
A88: 46115
A89: 46116
A90: 46117 | B90: Coal India Story | H90: to be shot - Wed.
B93: Coal india - story | C93: Shorts | D93: @raghav
B94: what's up with energy stocks
B95: power stocks - from oil & gas angle
B97: HDFC - 19th | H97: FMCG Shorts 1
B98: Indices comparison -- global | C98: shorts + static | H98: FMCG Shorts 2
B99: 2 IPOs
B100: Sachee Trivedi - (moneycontrol) | H100: IT Shorts 2
B101: IT & AI commentary
B102: Stock market crash - how much money are investors losing
B107: Investing like Stalwart - Nalanda | C107: Trying something unique on Main - We need to build another IP

Sheet Telugu
A1: Go live dates | B1: LF | C1: Shorts | D1: Status | E1: Assets | F1: POC | G1: Shoot
A2: 46031 | B2: SIP | D2: Published
A3: 46038 | B3: ETFs | D3: Published
A4: 46045 | B4: FD vs Arbitrage | D4: Published
A5: 46056 | B5: Parag Parikh | D5: Published
A6: 46064 | B6: Shipbuilding | D6: Published
A7: 46071 | C7: ETF Craze | D7: Ready
A8: 46072 | C8: iNAV | D8: Ready
A9: 46078 | B9: Data centres | D9: Published
A10: 46098 | B10: Why REITs & InvITs Are Exploding in India | D10: Published | E10: https://docs.google.com/document/d/1CbEUXbmdehVWln5320unAJgxbFL68hrksLaQThxj6fQ/edit?tab=t.88fe7l607bpa
A11: 46099 | C11: Checklist for InvITs | D11: Published | E11: https://docs.google.com/document/d/1CbEUXbmdehVWln5320unAJgxbFL68hrksLaQThxj6fQ/edit?tab=t.88fe7l607bpa
A12: 46102 | B12: 9 Stocks that FIIs & DIIs are buying in India right now | D12: Published | E12: https://docs.google.com/document/d/1CbEUXbmdehVWln5320unAJgxbFL68hrksLaQThxj6fQ/edit?tab=t.146rj0ckpmuw
A13: 46103
A14: 46105 | B14: 5 Undervalued Indian Stocks in 2026 | D14: Published | E14: https://docs.google.com/document/d/1CbEUXbmdehVWln5320unAJgxbFL68hrksLaQThxj6fQ/edit?tab=t.ud32fr920vjl
A15: 46109 | B15: Product Video
A16: 46113 | B16: Why MRF is India's Most Expensive Stock | D16: Ready | E16: https://docs.google.com/document/d/1CbEUXbmdehVWln5320unAJgxbFL68hrksLaQThxj6fQ/edit?tab=t.jm2qlau6oihv
A17: 46114 | C17: MRF Short 1 | D17: Ready | E17: https://docs.google.com/document/d/1CbEUXbmdehVWln5320unAJgxbFL68hrksLaQThxj6fQ/edit?tab=t.jm2qlau6oihv
A18: 46115 | C18: MRF Short 2 | D18: Ready | E18: https://docs.google.com/document/d/1CbEUXbmdehVWln5320unAJgxbFL68hrksLaQThxj6fQ/edit?tab=t.jm2qlau6oihv
A19: 46116 | B19: We tested Multi-Asset Funds for 2026 | D19: Edit WIP | E19: https://docs.google.com/document/d/1CbEUXbmdehVWln5320unAJgxbFL68hrksLaQThxj6fQ/edit?tab=t.5zg7dq41hav8
A20: 46117 | C20: Milti-Asset Short 1 | D20: Edit WIP | E20: https://docs.google.com/document/d/1CbEUXbmdehVWln5320unAJgxbFL68hrksLaQThxj6fQ/edit?usp=sharing
A21: 46120 | B21: What's up with banking stocks 2026 | D21: Edit WIP | E21: https://docs.google.com/document/d/1FKa0wtZRqfwQl3olJA2e3-ityjVXzzl-mDqH-YuieMA/edit?usp=sharing
A22: 46121 | C22: Short 1 | D22: Edit WIP | E22: https://docs.google.com/document/d/1FKa0wtZRqfwQl3olJA2e3-ityjVXzzl-mDqH-YuieMA/edit?usp=sharing
A23: 46122 | C23: Short 2 | D23: Edit WIP | E23: https://docs.google.com/document/d/1FKa0wtZRqfwQl3olJA2e3-ityjVXzzl-mDqH-YuieMA/edit?usp=sharing
A24: 46123 | B24: Are Hospital Stocks the Next Multibagger? | D24: Edit WIP | E24: https://docs.google.com/document/d/1FKa0wtZRqfwQl3olJA2e3-ityjVXzzl-mDqH-YuieMA/edit?usp=sharing
A25: 46124 | C25: Short 1 | D25: Edit WIP | E25: https://docs.google.com/document/d/1FKa0wtZRqfwQl3olJA2e3-ityjVXzzl-mDqH-YuieMA/edit?usp=sharing
A26: 46125 | C26: Short 2 | D26: Edit WIP | E26: https://docs.google.com/document/d/1FKa0wtZRqfwQl3olJA2e3-ityjVXzzl-mDqH-YuieMA/edit?usp=sharing
A27: 46127 | B27: We Tested Retirement Investing for 25 Years | D27: Edit WIP | E27: https://docs.google.com/document/d/1FKa0wtZRqfwQl3olJA2e3-ityjVXzzl-mDqH-YuieMA/edit?usp=sharing
A28: 46128 | C28: Short 1 | D28: Edit WIP | E28: https://docs.google.com/document/d/1FKa0wtZRqfwQl3olJA2e3-ityjVXzzl-mDqH-YuieMA/edit?usp=sharing
A29: 46129 | C29: Short 2 | D29: Edit WIP | E29: https://docs.google.com/document/d/1FKa0wtZRqfwQl3olJA2e3-ityjVXzzl-mDqH-YuieMA/edit?usp=sharing
A30: 46130 | B30: How to Invest Lumpsum? ₹50 Lakh Real Case Study | D30: Edit WIP | E30: https://docs.google.com/document/d/1FKa0wtZRqfwQl3olJA2e3-ityjVXzzl-mDqH-YuieMA/edit?usp=sharing
A31: 46131 | C31: Short 1 | D31: Edit WIP | E31: https://docs.google.com/document/d/1FKa0wtZRqfwQl3olJA2e3-ityjVXzzl-mDqH-YuieMA/edit?usp=sharing
A32: 46134 | B32: Does Timing Matter in Investment? | D32: Edit WIP | E32: https://docs.google.com/document/d/1FKa0wtZRqfwQl3olJA2e3-ityjVXzzl-mDqH-YuieMA/edit?usp=sharing
D33: Edit WIP | E33: https://docs.google.com/document/d/1FKa0wtZRqfwQl3olJA2e3-ityjVXzzl-mDqH-YuieMA/edit?usp=sharing

Sheet Comp analysis
A1: Competitor analysis
A2: Channels | B2: Subscribers | C2: Freq. of LF | D2: Freq. of SF | E2: Median views LF | F2: Median views SF | G2: Outlier topics | H2: Long vs Shorts View%
H3: LF | I3: Shorts
A4: https://www.youtube.com/@torahulj/ | H4: 0.62 | I4: 0.38
A5: https://www.youtube.com/@namaskarprasad/ | B5: 2.65M

Sheet Invs Supply Analytics
A1: NOVEMBER
A2: Supply
A3: Content type | B3: Month | C3: Videos published | D3: Likes | E3: Shares | F3: Comments added | G3: Average percentage viewed (%) | H3: Subscribers | I3: Views
A4: Shorts | B4: Nov | C4: 12 | D4: 604 | E4: 58 | F4: 10 | G4: 54.22 | H4: 84 | I4: 15418
A5: Videos | B5: Nov | C5: 5 | D5: 2689 | E5: 1590 | F5: 274 | G5: 32.3 | H5: 3487 | I5: 82942
A6: Other | B6: Nov | D6: 0 | E6: 0 | F6: 0 | H6: 608 | I6: 0
A7: Total | B7: Nov | C7: 17 | D7: 3293 | E7: 1648 | F7: 284 | G7: 32.51 | H7: 4179 | I7: 98360
A9: Shorts | B9: Dec | C9: 16 | D9: 1453 | E9: 147 | F9: 44 | G9: 59.37 | H9: 85 | I9: 27750
A10: Videos | B10: Dec | C10: 7 | D10: 2107 | E10: 1015 | F10: 185 | G10: 30.73 | H10: 1547 | I10: 53924
A11: Other | B11: Dec | D11: 0 | E11: 0 | F11: 0 | H11: 467 | I11: 0
A12: Total | B12: Dec | C12: 23 | D12: 3560 | E12: 1162 | F12: 229 | G12: 31.59 | H12: 2099 | I12: 81674
A14: Shorts | B14: Jan | C14: 11 | D14: 791 | E14: 131 | F14: 24 | G14: 59.64 | H14: 40 | I14: 17746
A15: Videos | B15: Jan | C15: 7 | D15: 4231 | E15: 1887 | F15: 206 | G15: 32.37 | H15: 3384 | I15: 126732
A16: Other | B16: Jan | D16: 0 | E16: 0 | F16: 0 | H16: 696 | I16: 0
A17: Total | B17: Jan | C17: 18 | D17: 5022 | E17: 2018 | F17: 230 | G17: 32.56 | H17: 4120 | I17: 144478
A19: Shorts | B19: Feb | C19: 16 | D19: 1453 | E19: 147 | F19: 44 | G19: 59.37 | H19: 85 | I19: 27750
A20: Videos | B20: Feb | C20: 7 | D20: 2107 | E20: 1015 | F20: 185 | G20: 30.73 | H20: 1547 | I20: 53924
A21: Other | B21: Feb | D21: 0 | E21: 0 | F21: 0 | H21: 467 | I21: 0
A22: Total | B22: Feb | C22: 23 | D22: 3560 | E22: 1162 | F22: 229 | G22: 31.59 | H22: 2099 | I22: 81674

Sheet Analytics - Inv Dump
A1: Video title | B1: Video publish time | C1: Month | D1: Duration | E1: Average percentage viewed (%) | F1: Likes | G1: Shares | H1: Comments added | I1: Views | J1: Watch time (hours) | K1: Subscribers | L1: Impressions | M1: Impressions click-through rate (%)
E2: 32.51 | F2: 3293 | G2: 1648 | H2: 284 | I2: 98360 | J2: 4502.6133 | K2: 4179 | L2: 1112807 | M2: 5.74
A3: Don’t miss these 2 sectors before they explode in India! | B3: Nov 6, 2025 | C3: November | D3: 623 | E3: 32.34 | F3: 1584 | G3: 1220 | H3: 180 | I3: 59564 | J3: 3333.4297 | K3: 2491 | L3: 733193 | M3: 6.34
A4: Why Investors pay 100x for Dmart… but only 7x for Coal India| Reality of PE Ratio | B4: Nov 14, 2025 | C4: November | D4: 503 | E4: 37.07 | F4: 483 | G4: 156 | H4: 32 | I4: 10457 | J4: 541.6922 | K4: 441 | L4: 175350 | M4: 4.21
A5: The ROCE Mistake Every Investor Makes | B5: Nov 20, 2025 | C5: November | D5: 351 | E5: 38.88 | F5: 255 | G5: 74 | H5: 17 | I5: 4562 | J5: 172.9385 | K5: 174 | L5: 61360 | M5: 5.56
A6: What should Indian investors do? - Is the market overvalued? | B6: Nov 28, 2025 | C6: November | D6: 530 | E6: 35.13 | F6: 129 | G6: 48 | H6: 12 | I6: 3601 | J6: 186.2324 | K6: 76 | L6: 50508 | M6: 5.31
A7: Don’t buy gold without watching this (Smart Investor Guide) | B7: Nov 1, 2025 | C7: November | D7: 582 | E7: 18.9 | F7: 124 | G7: 50 | H7: 19 | I7: 2656 | J7: 81.1386 | K7: 264 | L7: 28429 | M7: 3.58
A8: 46 IPOs. ₹90,000 Crore Raised. Here’s the TRUTH nobody’s telling You. | B8: Nov 24, 2025 | C8: November | D8: 915 | E8: 20.94 | F8: 114 | G8: 42 | H8: 14 | I8: 2102 | J8: 111.8755 | K8: 41 | L8: 31502 | M8: 4.14
A9: P/E Ratio explained in 80 seconds (simplest way ever!) | B9: Nov 18, 2025 | C9: November | D9: 93 | E9: 55.35 | F9: 72 | G9: 7 | H9: 1 | I9: 1549 | J9: 10.6208 | K9: 8 | L9: 3742 | M9: 5.24
A10: Stop misreading PE ratio! | B10: Nov 17, 2025 | C10: November | D10: 80 | E10: 41.88 | F10: 63 | G10: 5 | H10: 1 | I10: 1675 | J10: 6.9997 | K10: 8 | L10: 2962 | M10: 4.19
A11: How IPOs trick investors: The exit game explained | B11: Nov 26, 2025 | C11: November | D11: 81 | E11: 49.05 | F11: 62 | G11: 8 | H11: 0 | I11: 1209 | J11: 5.2129 | K11: 3 | L11: 2025 | M11: 4.59
A12: Why TCS earns ₹64.6 from every ₹100 | ROCE explained | B12: Nov 21, 2025 | C12: November | D12: 61 | E12: 54.22 | F12: 58 | G12: 3 | H12: 0 | I12: 1326 | J12: 6.543 | K12: 11 | L12: 3695 | M12: 5.44
A13: Is 13% ROCE bad? Not for L&T! Here’s why | B13: Nov 22, 2025 | C13: November | D13: 51 | E13: 64.95 | F13: 57 | G13: 2 | H13: 0 | I13: 1534 | J13: 6.2142 | K13: 12 | L13: 2599 | M13: 5.62
A14: These companies are changing how India builds EVERYTHING! | B14: Nov 10, 2025 | C14: November | D14: 55 | E14: 47.3 | F14: 56 | G14: 8 | H14: 2 | I14: 1561 | J14: 6.4077 | K14: 14 | L14: 3115 | M14: 5.55
... A62: PE 103 vs 51.5 - The Dmart Difference #stocks #trading | B62: Nov 16, 2025 | C62: December | D62: 64 | E62: 54.67 | F62: 1 | G62: 0 | H62: 0 | I62: 27 | J62: 0.1024 | K62: 0 | L62: 661 | M62: 0.45
A63: Where to INVEST in 2026? - Gold vs Silver vs Stocks vs Bonds | B63: Jan 3, 2026 | C63: December | D63: 629 | E63: 9.59 | F63: 0 | G63: 0 | H63: 0 | I63: 1 | J63: 0.0167 | K63: 0 | L63: 0
A65: 9 Stocks that FIIs & DIIs are buying in India right now | Institutional investing | B65: Jan 18, 2026 | C65: January | D65: 739 | E65: 32.74 | F65: 1603 | G65: 818 | H65: 55 | I65: 50627 | J65: 3402.2831 | K65: 1775 | L65: 623679 | M65: 6.31
A66: 5 Evergreen Stocks to invest & forget | India’s hidden compounders | B66: Jan 28, 2026 | C66: January | D66: 666 | E66: 32.31 | F66: 698 | G66: 296 | H66: 31 | I66: 22636 | J66: 1353.2084 | K66: 377 | L66: 181454 | M66: 9.73
A67: 5 Undervalued High-Growth Indian Stocks | India's Hidden Gems 🇮🇳 | B67: Jan 25, 2026 | C67: January | D67: 697 | E67: 32.79 | F67: 589 | G67: 196 | H67: 14 | I67: 11336 | J67: 719.6451 | K67: 303 | L67: 86701 | M67: 9.17
A68: Missed the Gold-Silver rally? But is it just the start? | B68: Jan 21, 2026 | C68: January | D68: 815 | E68: 31.39 | F68: 428 | G68: 201 | H68: 24 | I68: 15322 | J68: 1088.8093 | K68: 362 | L68: 202047 | M68: 6.06
A69: 4 Sectors to look at - Watch this before Budget 2026 | B69: Jan 23, 2026 | C69: January | D69: 703 | E69: 34.69 | F69: 324 | G69: 124 | H69: 30 | I69: 7846 | J69: 531.4359 | K69: 143 | L69: 88937 | M69: 5.65
A70: ITC fell 15%: What should investors do? | Tobacco Stocks Crash | B70: Jan 10, 2026 | C70: January | D70: 651 | E70: 32.09 | F70: 236 | G70: 76 | H70: 26 | I70: 7833 | J70: 454.5702 | K70: 205 | L70: 99773 | M70: 4.95
A71: Where to INVEST in 2026? - Gold vs Silver vs Stocks vs Bonds | B71: Jan 3, 2026 | C71: January | D71: 629 | E71: 25.39 | F71: 155 | G71: 84 | H71: 12 | I71: 3704 | J71: 164.326 | K71: 68 | L71: 41058 | M71: 3.93
A72: Stocks that win from India-EU Trade Deal! | B72: Jan 31, 2026 | C72: January | D72: 162 | E72: 61.14 | F72: 93 | G72: 21 | H72: 3 | I72: 1214 | J72: 17.4358 | K72: 2 | L72: 5449 | M72: 4.28
A73: You are missing this Global ETF! 🤷‍♀️ | B73: Jan 2, 2026 | C73: January | D73: 56 | E73: 63.08 | F73: 83 | G73: 14 | H73: 1 | I73: 1730 | J73: 10.6116 | K73: 6 | L73: 8785 | M73: 6.68
A74: 3 ETFs for your 2026 Portfolio | B74: Dec 27, 2025 | C74: January | D74: 415 | E74: 34.86 | F74: 82 | G74: 25 | H74: 8 | I74: 2850 | J74: 114.5133 | K74: 46 | L74: 28825 | M74: 7.29
A75: Gold or Silver - This ratio will answer! | B75: Jan 22, 2026 | C75: January | D75: 48 | E75: 66.43 | F75: 70 | G75: 9 | H75: 2 | I75: 1869 | J75: 8.1067 | K75: 5 | L75: 3673 | M75: 4.82
A76: ITC fell 15% in 2017 but then it doubled. Will history repeat? | B76: Jan 14, 2026 | C76: January | D76: 74 | E76: 55.74 | F76: 67 | G76: 5 | H76: 3 | I76: 1633 | J76: 10.6569 | K76: 3 | L76: 6701 | M76: 5.37
... A185: Tata Motors vs Asian Paints vs Vodafone: What ROE really reveals! | B185: Dec 17, 2025 | C185: February | D185: 568 | E185: 33.22 | F185: 0 | G185: 0 | H185: 0 | I185: 22 | J185: 1.1532 | K185: 0 | L185: 1167 | M185: 1.71
A186: ICICI Pru AMC IPO: The company that manages ₹10 LAKH Crore! | B186: Dec 12, 2025 | C186: February | D186: 105 | F186: 0 | G186: 0 | H186: 0 | I186: 2 | J186: 0.0016 | K186: 0 | L186: 104 | M186: 0
A187: 46 IPOs. ₹90,000 Crore Raised. Here’s the TRUTH nobody’s telling You. | B187: Nov 24, 2025 | C187: February | D187: 915 | E187: 0.69 | F187: 0 | G187: 0 | H187: 0 | I187: 3 | J187: 0.0053 | K187: 0 | L187: 639 | M187: 0
A188: 82% returns from a 150-year-old company? 👀 | B188: Dec 25, 2025 | C188: February | D188: 60 | E188: 28.73 | F188: 0 | G188: 0 | H188: 0 | I188: 42 | J188: 0.1019 | K188: 0 | L188: 157 | M188: 1.27
A189: Part 2 is here and it's bigger #emerging #trending | B189: Dec 6, 2025 | C189: February | D189: 18 | E189: 77.22 | F189: 0 | G189: 0 | H189: 0 | I189: 4 | J189: 0.0042 | K189: 0 | L189: 74 | M189: 1.35
A190: Stocks or Gold - Which actually made more money? | B190: Nov 7, 2025 | C190: February | D190: 76 | E190: 8.95 | F190: 0 | G190: 0 | H190: 0 | I190: 3 | J190: 0.0023 | K190: 0 | L190: 48 | M190: 2.08
A191: Don’t buy gold without watching this (Smart Investor Guide) | B191: Nov 1, 2025 | C191: February | D191: 582 | E191: 22.18 | F191: 0 | G191: 0 | H191: 0 | I191: 27 | J191: 0.9682 | K191: 0 | L191: 383 | M191: 3.39
A192: Why are Indians paying 3× more for the SAME companies? | B192: Nov 29, 2025 | C192: February | D192: 86 | E192: 88.26 | F192: 0 | G192: 0 | H192: 0 | I192: 4 | J192: 0.0216 | K192: 0 | L192: 94 | M192: 1.06
A193: DIIs & FIIs Explained! Why Institutional Investing matters to us? | B193: Jan 20, 2026 | C193: February | D193: 60 | E193: 62.32 | F193: 0 | G193: 0 | H193: 0 | I193: 33 | J193: 0.1454 | K193: 0 | L193: 473 | M193: 1.27
A194: India's next big investment opportunity | B194: Dec 8, 2025 | C194: February | D194: 60 | F194: 0 | G194: 0 | H194: 0 | I194: 3 | J194: 0.0011 | K194: 0 | L194: 133 | M194: 0
A195: Where to INVEST in 2026? - Gold vs Silver vs Stocks vs Bonds | B195: Jan 3, 2026 | C195: February | D195: 629 | E195: 21.1 | F195: -1 | G195: 0 | H195: 0 | I195: 51 | J195: 1.8806 | K195: 0 | L195: 1229 | M195: 1.71
A196: Highest gainer of 2025 but nobody noticed it! 😯 | B196: Dec 23, 2025 | C196: February | D196: 73 | E196: 53.3 | F196: -1 | G196: 0 | H196: 0 | I196: 11 | J196: 0.0559 | K196: 0 | L196: 123 | M196: 2.44
A197: The ROCE Mistake Every Investor Makes | B197: Nov 20, 2025 | C197: February | D197: 351 | E197: 39.39 | F197: -1 | G197: 0 | H197: 0 | I197: 39 | J197: 1.4979 | K197: 0 | L197: 1029 | M197: 2.72
A198: The 5-Second test that exposes weak companies (Most investors ignore this!) | B198: Dec 14, 2025 | C198: February | D198: 49 | E198: 88.3 | F198: -1 | G198: 1 | H198: 0 | I198: 12 | J198: 0.0723 | K198: 0 | L198: 139 | M198: 0.72
A199: Silver: best performing asset of 2025. But what about 2026? | B199: Jan 5, 2026 | C199: February | D199: 54 | L199: 4 | M199: 0
A200: ITC vs GST 2026: Why ₹70,000 Crore vanished in 2 days | B200: Jan 13, 2026 | C200: February | D200: 63 | L200: 7 | M200: 0

Sheet Input
A1: Channel Name | B1: Month Target | C1: Current Views | D1: Days Left | E1: LF Target | F1: LF Published | G1: LF Remaining | H1: SF Target | I1: SF Published | J1: SF Remaining | M1: Total LF Views (last 30 days) | N1: Total SF Views (last 30 days) | O1: LF Videos (last 30 days) | P1: SF Videos (last 30 days) | Q1: Rolling Avg per LF | R1: Rolling Avg per SF | S1: Historical LF Contribution % | T1: Historical SF Contribution %
A2: Angel One for Investors | B2: 360000 | C2: 146032 | D2: 15 | E2: 8 | F2: 4 | G2: =E2-F2 -> 4 | H2: 16 | I2: 7 | J2: =H2-I2 -> 9 | M2: 189092 | N2: 28367 | O2: 9 | P2: 12 | Q2: =IF(O2>0, M2/O2, 0) -> 21010.222 | R2: =IF(P2>0, N2/P2, 0) -> 2363.9167 | S2: =M2/(M2+N2) -> 0.86955242 | T2: =N2/(M2+N2) -> 0.13044758
A3: Angel One Main | B3: 900000 | C3: 208251 | D3: 15 | E3: 8 | F3: 4 | G3: =E3-F3 -> 4 | H3: 24 | I3: 12 | J3: =H3-I3 -> 12 | M3: 182616 | N3: 228641

Sheet Live Dashboard
A1: Angel One for Investors | B1: Target Views | C1: =Input!B2 -> 360000
B2: Current Views | C2: =Input!C2 -> 146032
B3: Views Shortfall | C3: =Input!B2-Input!C2 -> 213968
B4: Days remaining | C4: =Input!D2 -> 15
B6: Content Type needed | C6: Published | D6: Target | E6: Remaining
B7: Long form | C7: =Input!F2 -> 4 | D7: =Input!E2 -> 8 | E7: =Input!G2 -> 4
B8: Shorts | C8: =Input!I2 -> 7 | D8: =Input!H2 -> 16 | E8: =Input!J2 -> 9
B10: Projected Views (current average) | C10: =(Input!G2 * Input!Q2) + (Input!J2 * Input!R2) + Input!C2 -> 251348.14
B11: Projected Shortfall | C11: =Input!B2 - C10 -> 108651.86
B12: Shortfall aligned to LF | C12: =IF(C11>0, C11 * Input!S2, 0) -> 94478.489
B13: Shortfall aligned to SF | C13: =IF(C11>0, C11 * Input!T2, 0) -> 14173.372
B14: Average views needed per LF to close gap | C14: =IF(Input!G2>0, (C12 + (Input!G2 * Input!Q2)) / Input!G2, 0) -> 44629.844
B15: Avg Views Needed per SF to close gap | C15: =IF(Input!J2>0, (C13 + (Input!J2 * Input!R2)) / Input!J2, 0) -> 3938.7358
B16: % of target achieved | C16: =(Input!C2/Input!B2)*100 -> 40.564444

Sheet Input 1
A1: Channel Name | B1: Month Target | C1: Current Views | D1: Days Left | E1: LF Target | F1: LF Published | G1: LF Remaining | H1: SF Target | I1: SF Published | J1: SF Remaining | M1: Total channel views (last 30 days) | N1: Views from published videos this month | O1: Residual views (old content) | P1: LF Videos published this month | Q1: SF Videos published this month | R1: LF views this month (new videos only) | S1: SF views this month (new videos only) | T1: 30-day rolling LF avg - new videos only | U1: 30-day rolling SF avg - new videos only
A2: Angel One for Investors | B2: 360000 | C2: 190381 | D2: 9 | E2: 8 | F2: 6 | G2: =E2-F2 -> 2 | H2: 16 | I2: 10 | J2: =H2-I2 -> 6 | M2: 213457 | N2: 122534 | O2: =M2-N2 -> 90923 | P2: 4 | Q2: 7 | R2: 105190 | S2: 17379 | T2: =IF(P2>0, R2/P2, 0) -> 26297.5 | U2: =IF(Q2>0, S2/Q2, 0) -> 2482.7143
A3: Angel One Main | B3: 900000 | C3: 208254 | D3: 15 | E3: 8 | F3: 4 | G3: =E3-F3 -> 4 | H3: 24 | I3: 12 | J3: =H3-I3 -> 12 | M3: 387186 | N3: 118968 | O3: =M3-N3 -> 268218 | P3: 4 | Q3: 12 | R3: 21664 | S3: 97327 | T3: =IF(P3>0, R3/P3, 0) -> 5416 | U3: =IF(Q3>0, S3/Q3, 0) -> 8110.5833

Sheet Live dashboard 1
A1: Angel One for Investors | B1: Target Views | C1: ='Input 1'!B2 -> 360000 | G1: Angel One Main | H1: Target Views | I1: ='Input 1'!B3 -> 900000
B2: Current Views | C2: ='Input 1'!C2 -> 190381 | H2: Current Views | I2: ='Input 1'!C3 -> 208254
B3: Views Shortfall | C3: ='Input 1'!B2-'Input 1'!C2 -> 169619 | H3: Views Shortfall | I3: ='Input 1'!B3-'Input 1'!C3 -> 691746
B4: Days remaining | C4: ='Input 1'!D2 -> 9 | H4: Days remaining | I4: 15
B6: Content Type needed | C6: Published | D6: Target | E6: Remaining | H6: Content Type needed | I6: Published | J6: Target | K6: Remaining
B7: Long form | C7: ='Input 1'!F2 -> 6 | D7: ='Input 1'!E2 -> 8 | E7: ='Input 1'!G2 -> 2 | H7: Long form | I7: ='Input 1'!F3 -> 4 | J7: ='Input 1'!E3 -> 8 | K7: ='Input 1'!G3 -> 4
B8: Shorts | C8: ='Input 1'!I2 -> 10 | D8: ='Input 1'!H2 -> 16 | E8: ='Input 1'!J2 -> 6 | H8: Shorts | I8: ='Input 1'!I3 -> 12 | J8: ='Input 1'!H3 -> 24 | K8: ='Input 1'!J3 -> 12
B10: Realised Projected Total Views (current average) | C10: ='Input 1'!C2 +('Input 1'!G2*'Input 1'!T2) + ('Input 1'!J2*'Input 1'!U2) -> 257872.29 | H10: Realised Projected Total Views (current average) | I10: ='Input 1'!C3 +('Input 1'!G3*'Input 1'!T3) + ('Input 1'!J3*'Input 1'!U3) -> 327245
B11: Projected Shortfall | C11: ='Input 1'!B2 - C10 -> 102127.71 | H11: Projected Shortfall | I11: ='Input 1'!B3 - I10 -> 572755
B12: Shortfall aligned to LF | C12: =IF(('Input 1'!B2 - ('Input 1'!C2 + ('Input 1'!G2 * 'Input 1'!T2) + ('Input 1'!J2 * 'Input 1'!U2))) > 0, ('Input 1'!B2 - ('Input 1'!C2 + ('Input 1'!G2 * 'Input 1'!T2) + ('Input 1'!J2 * 'Input 1'!U2))) * ('Input 1'!R2 / ('Input 1'!R2 + 'Input 1'!S2)), 0) -> 87647.074 | H12: Shortfall aligned to LF | I12: =IF(('Input 1'!B3 - ('Input 1'!C3 + ('Input 1'!G3 * 'Input 1'!T3) + ('Input 1'!J3 * 'Input 1'!U3))) > 0, ('Input 1'!B3 - ('Input 1'!C3 + ('Input 1'!G3 * 'Input 1'!T3) + ('Input 1'!J3 * 'Input 1'!U3))) * ('Input 1'!R3 / ('Input 1'!R3 + 'Input 1'!S3)), 0) -> 104278.18
B13: Shortfall aligned to SF | C13: =IF(('Input 1'!B2 - ('Input 1'!C2 + ('Input 1'!G2 * 'Input 1'!T2) + ('Input 1'!J2 * 'Input 1'!U2))) > 0, ('Input 1'!B2 - ('Input 1'!C2 + ('Input 1'!G2 * 'Input 1'!T2) + ('Input 1'!J2 * 'Input 1'!U2))) * ('Input 1'!S2 / ('Input 1'!R2 + 'Input 1'!S2)), 0) -> 14480.64 | H13: Shortfall aligned to SF | I13: =IF(('Input 1'!B3 - ('Input 1'!C3 + ('Input 1'!G3 * 'Input 1'!T3) + ('Input 1'!J3 * 'Input 1'!U3))) > 0, ('Input 1'!B3 - ('Input 1'!C3 + ('Input 1'!G3 * 'Input 1'!T3) + ('Input 1'!J3 * 'Input 1'!U3))) * ('Input 1'!S3 / ('Input 1'!R3 + 'Input 1'!S3)), 0) -> 468476.83
B14: Average views needed per LF to close gap | C14: =IF('Input 1'!G2 > 0, 'Input 1'!T2 + (C12 / 'Input 1'!G2), 0) -> 70121.037 | H14: Average views needed per LF to close gap | I14: =IF('Input 1'!G3 > 0, 'Input 1'!T3 + (I12 / 'Input 1'!G3), 0) -> 31485.544
B15: Avg Views Needed per SF to close gap | C15: =IF('Input 1'!J2 > 0, 'Input 1'!U2 + (C13 / 'Input 1'!J2), 0) -> 4896.1543 | H15: Avg Views Needed per SF to close gap | I15: =IF('Input 1'!J3 > 0, 'Input 1'!U3 + (I13 / 'Input 1'!J3), 0) -> 47150.319
B16: % of target achieved | C16: =TEXT('Input 1'!C2 / 'Input 1'!B2, "0.0%") -> 52.9% | H16: % of target achieved | I16: =TEXT('Input 1'!C3 / 'Input 1'!B3, "0.0%") -> 23.1%
